script/adt_training.py
script/clean_training.py
script/custat_training.py
script/run_all.ps1
script/standardat_training.py
script/test.py
script/testing_framework.py
script/warmup_round.py
script/airtk/__init__.py
script/airtk/__main__.py
script/airtk/data.py
script/airtk/helper_functions.py
script/airtk/loss.py
script/airtk/util.py
script/airtk/attack/__init__.py
script/airtk/attack/apgd.py
script/airtk/attack/base.py
script/airtk/attack/fgsm.py
script/airtk/attack/pgd.py
script/airtk/attack/util.py
script/airtk/attack/MAIR/LICENSE.md
script/airtk/attack/MAIR/__init__.py
script/airtk/attack/MAIR/attack.py
script/airtk/attack/MAIR/eotpgd.py
script/airtk/attack/MAIR/try_them_all.py
script/airtk/attack/MAIR/attacks/__init__.py
script/airtk/attack/MAIR/attacks/attack.py
script/airtk/attack/MAIR/attacks/attacks/__init__.py
script/airtk/attack/MAIR/attacks/attacks/_differential_evolution.py
script/airtk/attack/MAIR/attacks/attacks/apgd.py
script/airtk/attack/MAIR/attacks/attacks/apgdt.py
script/airtk/attack/MAIR/attacks/attacks/autoattack.py
script/airtk/attack/MAIR/attacks/attacks/bim.py
script/airtk/attack/MAIR/attacks/attacks/cw.py
script/airtk/attack/MAIR/attacks/attacks/deepfool.py
script/airtk/attack/MAIR/attacks/attacks/difgsm.py
script/airtk/attack/MAIR/attacks/attacks/eaden.py
script/airtk/attack/MAIR/attacks/attacks/eadl1.py
script/airtk/attack/MAIR/attacks/attacks/eotpgd.py
script/airtk/attack/MAIR/attacks/attacks/fab.py
script/airtk/attack/MAIR/attacks/attacks/ffgsm.py
script/airtk/attack/MAIR/attacks/attacks/fgsm.py
script/airtk/attack/MAIR/attacks/attacks/gn.py
script/airtk/attack/MAIR/attacks/attacks/jitter.py
script/airtk/attack/MAIR/attacks/attacks/jsma.py
script/airtk/attack/MAIR/attacks/attacks/mifgsm.py
script/airtk/attack/MAIR/attacks/attacks/nifgsm.py
script/airtk/attack/MAIR/attacks/attacks/onepixel.py
script/airtk/attack/MAIR/attacks/attacks/pgd.py
script/airtk/attack/MAIR/attacks/attacks/pgdl2.py
script/airtk/attack/MAIR/attacks/attacks/pgdrs.py
airtk-0.1.2.dist-info/METADATA
airtk-0.1.2.dist-info/WHEEL
airtk-0.1.2.dist-info/licenses/AUTHORS.md
airtk-0.1.2.dist-info/licenses/LICENSE.md
airtk-0.1.2.dist-info/RECORD
