Metadata-Version: 2.3
Name: airtk
Version: 0.1.2
Summary: Comprehensive and simple framework for conducting AI robustness experiments
Project-URL: Homepage, https://github.com/LAiSR-SK/AiRobustnessTestingKit-AiR-TK-
Project-URL: Issues, https://github.com/LAiSR-SK/AiRobustnessTestingKit-AiR-TK-/issues
Author-email: Deirdre Jost <jostdb@miamioh.edu>, Steven Chiacchira <chiaccsa@miamioh.edu>
License-File: AUTHORS.md
License-File: LICENSE.md
Classifier: Environment :: GPU :: NVIDIA CUDA :: 11.8
Classifier: License :: OSI Approved :: MIT License
Classifier: Operating System :: Microsoft :: Windows :: Windows 10
Classifier: Programming Language :: Python :: 3
Requires-Python: ==3.9
Requires-Dist: huggingface-hub>=0.24.0
Requires-Dist: networkx>=3.1
Requires-Dist: pytorch>=2.1.1
Requires-Dist: pyyaml>=6.0.0
